awx/__init__.py
awx/awx_discrete_field.py
awx/awx_geos_image.py
awx/awx_grid_field.py
awx/awx_polar_image.py
awx/tests/test_reader.py
awx/tests/__pycache__/test_reader.cpython-37-pytest-7.1.2.pyc
awx/tests/data/ANI_IR2_R01_20230217_0800_FY2G.AWX
awx/tests/data/ANI_VIS_R02_20230217_1000_FY2G.AWX
awx/tests/data/ANI_VIS_R02_20230217_1000_FY2G.nc
awx/tests/data/FY2E_CTA_MLT_OTG_20170126_0130.AWX
awx/tests/data/FY2G_TBB_IR1_OTG_20150729_0000.AWX
awx-0.1.1.dist-info/LICENSE
awx-0.1.1.dist-info/METADATA
awx-0.1.1.dist-info/WHEEL
awx-0.1.1.dist-info/entry_points.txt
awx-0.1.1.dist-info/top_level.txt
awx-0.1.1.dist-info/RECORD
